irisml/tasks/create_azure_computervision_caption_model.py
irisml/tasks/create_azure_computervision_classification_model.py
irisml/tasks/create_azure_computervision_custom_model.py
irisml/tasks/create_azure_computervision_ocr_model.py
irisml/tasks/create_azure_computervision_product_recognizer_model.py
irisml/tasks/create_azure_computervision_vectorization_model.py
irisml/tasks/delete_azure_computervision_custom_model.py
irisml/tasks/train_azure_computervision_custom_model.py
irisml_tasks_azure_computervision-0.0.9.dist-info/LICENSE
irisml_tasks_azure_computervision-0.0.9.dist-info/METADATA
irisml_tasks_azure_computervision-0.0.9.dist-info/WHEEL
irisml_tasks_azure_computervision-0.0.9.dist-info/top_level.txt
irisml_tasks_azure_computervision-0.0.9.dist-info/RECORD
