Metadata-Version: 2.1
Name: irisml-tasks-azure-computervision
Version: 0.0.9
Summary: Azure Computer Vision API tasks for IrisML
Home-page: https://github.com/microsoft/irisml-tasks-azure-computervision
Author: irisdev
License: MIT
Requires-Python: >=3.8
License-File: LICENSE
Requires-Dist: irisml
Requires-Dist: Pillow
Requires-Dist: requests
Requires-Dist: tenacity
Requires-Dist: torchvision
